handymatt/util/__init__.py
handymatt/util/bookmarks_getter.py
handymatt/util/json_handler.py
handymatt/util/string_parser.py
handymatt_util-0.0.2.dist-info/METADATA
handymatt_util-0.0.2.dist-info/WHEEL
handymatt_util-0.0.2.dist-info/RECORD
